corvid/__init__.py
corvid/__main__.py
corvid-1.1.1.dist-info/LICENSE
corvid-1.1.1.dist-info/METADATA
corvid-1.1.1.dist-info/WHEEL
corvid-1.1.1.dist-info/entry_points.txt
corvid-1.1.1.dist-info/top_level.txt
corvid-1.1.1.dist-info/RECORD
