Metadata-Version: 2.2
Name: corvid
Version: 1.1.1
Summary: An opinionated simple static site generator
Home-page: https://github.com/di/corvid
Author: Dustin Ingram
Author-email: di@python.org
Keywords: static markdown
Classifier: Development Status :: 3 - Alpha
Classifier: Intended Audience :: Developers
Classifier: License :: OSI Approved :: Apache Software License
Classifier: Programming Language :: Python :: 3
Classifier: Programming Language :: Python :: 3.5
Classifier: Programming Language :: Python :: 3.6
Classifier: Programming Language :: Python :: 3.7
Classifier: Programming Language :: Python :: 3.8
Requires-Python: >=3.5, <4
License-File: LICENSE
Requires-Dist: click<=8.0,>=7.0
Requires-Dist: python-frontmatter>=0.5.0
Requires-Dist: Markdown>=3.1
Requires-Dist: jinja2>=2.10
Requires-Dist: watchdog>=0.9.0
Provides-Extra: test
Requires-Dist: pytest; extra == "test"
Requires-Dist: tox; extra == "test"
Dynamic: author
Dynamic: author-email
Dynamic: classifier
Dynamic: description
Dynamic: description-content-type
Dynamic: home-page
Dynamic: keywords
Dynamic: provides-extra
Dynamic: requires-dist
Dynamic: requires-python
Dynamic: summary
